tpc_logger/Log.py
tpc_logger/__init__.py
tpc_logger-2.5.0.dist-info/METADATA
tpc_logger-2.5.0.dist-info/WHEEL
tpc_logger-2.5.0.dist-info/top_level.txt
tpc_logger-2.5.0.dist-info/RECORD
