Metadata-Version: 2.1
Name: tpc-logger
Version: 2.5.0
Summary: A logger
Home-page: UNKNOWN
Author: Romain Osso
Author-email: romain.osso@theprogrammaticcompany.com
License: UNKNOWN
Platform: UNKNOWN
Requires-Dist: colorama
